delayed/__init__.py
delayed/constants.py
delayed/delay.py
delayed/keep_alive.py
delayed/logger.py
delayed/queue.py
delayed/sweeper.py
delayed/task.py
delayed/worker.py
delayed-1.2.0b1.dist-info/LICENSE
delayed-1.2.0b1.dist-info/METADATA
delayed-1.2.0b1.dist-info/WHEEL
delayed-1.2.0b1.dist-info/top_level.txt
delayed-1.2.0b1.dist-info/RECORD
