Metadata-Version: 2.1
Name: delayed
Version: 1.2.0b1
Summary: a simple but robust task queue
Home-page: https://github.com/keakon/delayed
Author: keakon
Author-email: keakon@gmail.com
Classifier: Development Status :: 4 - Beta
Classifier: Environment :: Console
Classifier: Intended Audience :: Developers
Classifier: License :: OSI Approved :: MIT License
Classifier: Operating System :: MacOS :: MacOS X
Classifier: Operating System :: POSIX
Classifier: Programming Language :: Python :: 2.7
Classifier: Programming Language :: Python :: 3
Classifier: Programming Language :: Python :: Implementation :: CPython
Classifier: Programming Language :: Python :: Implementation :: PyPy
Requires-Python: >=2.7
License-File: LICENSE
Requires-Dist: hiredis
Requires-Dist: redis
Requires-Dist: msgpack
